[
  {
    "Id": 1,
    "name": "Emma Johnson",
    "studentId": "STU001",
    "classId": 1,
    "className": "4A",
    "guardianName": "Michael Johnson",
    "guardianPhone": "+1 (555) 123-4567",
    "guardianEmail": "michael.johnson@email.com",
    "attendanceRate": 95,
    "overallGrade": "A-",
    "notes": "Excellent student with strong mathematical skills"
  },
  {
    "Id": 2,
    "name": "Liam Smith",
    "studentId": "STU002",
    "classId": 1,
    "className": "4A",
    "guardianName": "Sarah Smith",
    "guardianPhone": "+1 (555) 234-5678",
    "guardianEmail": "sarah.smith@email.com",
    "attendanceRate": 88,
    "overallGrade": "B+",
    "notes": "Creative student who excels in art and writing"
  },
  {
    "Id": 3,
    "name": "Olivia Brown",
    "studentId": "STU003",
    "classId": 1,
    "className": "4A",
    "guardianName": "David Brown",
    "guardianPhone": "+1 (555) 345-6789",
    "guardianEmail": "david.brown@email.com",
    "attendanceRate": 92,
    "overallGrade": "A",
    "notes": "Outstanding performance in all subjects"
  },
  {
    "Id": 4,
    "name": "Noah Davis",
    "studentId": "STU004",
    "classId": 1,
    "className": "4A",
    "guardianName": "Jennifer Davis",
    "guardianPhone": "+1 (555) 456-7890",
    "guardianEmail": "jennifer.davis@email.com",
    "attendanceRate": 85,
    "overallGrade": "B",
    "notes": "Shows improvement in reading comprehension"
  },
  {
    "Id": 5,
    "name": "Ava Wilson",
    "studentId": "STU005",
    "classId": 1,
    "className": "4A",
    "guardianName": "Robert Wilson",
    "guardianPhone": "+1 (555) 567-8901",
    "guardianEmail": "robert.wilson@email.com",
    "attendanceRate": 94,
    "overallGrade": "A-",
    "notes": "Strong leadership qualities and team player"
  },
  {
    "Id": 6,
    "name": "Ethan Miller",
    "studentId": "STU006",
    "classId": 2,
    "className": "4B",
    "guardianName": "Lisa Miller",
    "guardianPhone": "+1 (555) 678-9012",
    "guardianEmail": "lisa.miller@email.com",
    "attendanceRate": 90,
    "overallGrade": "B+",
    "notes": "Excellent in science and experiments"
  },
  {
    "Id": 7,
    "name": "Isabella Garcia",
    "studentId": "STU007",
    "classId": 2,
    "className": "4B",
    "guardianName": "Carlos Garcia",
    "guardianPhone": "+1 (555) 789-0123",
    "guardianEmail": "carlos.garcia@email.com",
    "attendanceRate": 87,
    "overallGrade": "B",
    "notes": "Bilingual student with great potential"
  },
  {
    "Id": 8,
    "name": "Mason Rodriguez",
    "studentId": "STU008",
    "classId": 2,
    "className": "4B",
    "guardianName": "Maria Rodriguez",
    "guardianPhone": "+1 (555) 890-1234",
    "guardianEmail": "maria.rodriguez@email.com",
    "attendanceRate": 91,
    "overallGrade": "A-",
    "notes": "Talented in music and creative arts"
  },
  {
    "Id": 9,
    "name": "Sophia Lee",
    "studentId": "STU009",
    "classId": 2,
    "className": "4B",
    "guardianName": "James Lee",
    "guardianPhone": "+1 (555) 901-2345",
    "guardianEmail": "james.lee@email.com",
    "attendanceRate": 96,
    "overallGrade": "A",
    "notes": "Top performer with excellent study habits"
  },
  {
    "Id": 10,
    "name": "William Anderson",
    "studentId": "STU010",
    "classId": 2,
    "className": "4B",
    "guardianName": "Amanda Anderson",
    "guardianPhone": "+1 (555) 012-3456",
    "guardianEmail": "amanda.anderson@email.com",
    "attendanceRate": 83,
    "overallGrade": "B-",
    "notes": "Needs additional support in mathematics"
  },
  {
    "Id": 11,
    "name": "Mia Taylor",
    "studentId": "STU011",
    "classId": 3,
    "className": "5A",
    "guardianName": "Kevin Taylor",
    "guardianPhone": "+1 (555) 123-4567",
    "guardianEmail": "kevin.taylor@email.com",
    "attendanceRate": 93,
    "overallGrade": "A-",
    "notes": "Excellent analytical thinking skills"
  },
  {
    "Id": 12,
    "name": "James Thomas",
    "studentId": "STU012",
    "classId": 3,
    "className": "5A",
    "guardianName": "Michelle Thomas",
    "guardianPhone": "+1 (555) 234-5678",
    "guardianEmail": "michelle.thomas@email.com",
    "attendanceRate": 89,
    "overallGrade": "B+",
    "notes": "Great participation in class discussions"
  },
  {
    "Id": 13,
    "name": "Charlotte Jackson",
    "studentId": "STU013",
    "classId": 4,
    "className": "5B",
    "guardianName": "Brian Jackson",
    "guardianPhone": "+1 (555) 345-6789",
    "guardianEmail": "brian.jackson@email.com",
    "attendanceRate": 94,
    "overallGrade": "A",
    "notes": "Natural leader with strong communication skills"
  },
  {
    "Id": 14,
    "name": "Benjamin White",
    "studentId": "STU014",
    "classId": 4,
    "className": "5B",
    "guardianName": "Rachel White",
    "guardianPhone": "+1 (555) 456-7890",
    "guardianEmail": "rachel.white@email.com",
    "attendanceRate": 86,
    "overallGrade": "B",
    "notes": "Shows creativity in problem-solving"
  },
  {
    "Id": 15,
    "name": "Amelia Harris",
    "studentId": "STU015",
    "classId": 5,
    "className": "3A",
    "guardianName": "Steven Harris",
    "guardianPhone": "+1 (555) 567-8901",
    "guardianEmail": "steven.harris@email.com",
    "attendanceRate": 92,
    "overallGrade": "A-",
    "notes": "Mature for her age with excellent behavior"
  }
]